{
    "Usernames": {
        "256769620336312320": {
            "TM2020 Username": "SMASHER_VAMSI",
            "TM2020 ID": "52ee751e-7c4a-4317-be17-3c96aad92b6b"
        },
        "84628323174461440": {
            "TM2020 Username": "HACHIKUKU",
            "TM2020 ID": "4be8d8fc-3c47-4f41-8e5e-1370092c263f"
        },
        "527497533916708874": {
            "TM2020 Username": "kunal1398",
            "TM2020 ID": "48e8de52-2473-4a1d-b095-190a79af5085"
        },
        "739024911062007861": {
            "TM2020 Username": "kaizer",
            "TM2020 ID": "1f5b7b22-35bc-4e61-9ebe-a72c61006e92"
        },
        "833587274359898133": {
            "TM2020 Username": "GamingFreak",
            "TM2020 ID": "3726ac41-c46e-473a-ab72-e0e5a50e9890"
        },
        "704365354008444939": {
            "TM2020 Username": "DynatimeX",
            "TM2020 ID": "cd185e2a-8351-49f5-8371-f31b11040970"
        },
        "742671912773353482": {
            "TM2020 Username": "OjasTM",
            "TM2020 Username Key": "A",
            "TM2020 ID": "a41f0623-47d0-43e6-8869-834ad150dfce"
        },
        "250257390643970059": {
            "TM2020 Username": "NottCurious",
            "TM2020 ID": "b73fe3d7-a92a-4a6d-ab9d-49005caec499"
        }
    }
}