{
    "Map Name": "Driti leik",
    "Author": "mimexdd",
    "Thumbnail URL": "https://prod.trackmania.core.nadeo.online/storageObjects/50195872-7c37-484f-8464-168f3d0f4a7a.jpg",
    "Download Link": "https://prod.trackmania.core.nadeo.online/storageObjects/50195872-7c37-484f-8464-168f3d0f4a7a.jpg",
    "UID": "qEkFv2XeLII2jQPWD7Yxbog9IBj",
    "Author Time": "0:43.572",
    "Gold Time": "0:47.000",
    "Silver Time": "0:53.000",
    "Bronze Time": "1:06.000",
    "WR Holder": "Insanity.TM",
    "WR Time": "0:43.305",
    "Nadeo Uploaded": "<t:1643370168:R>",
    "Mania Tags": null,
    "TMX Uploaded": null,
    "TMX Code": null,
    "Day": "07",
    "Month": "February"
}